setup_client_whl.py
client/__init__.py
client/client.py
client/client/__init__.py
client/client/add_contact.py
client/client/database.py
client/client/del_contact.py
client/client/main_window.py
client/client/main_window_conv.py
client/client/start_dialog.py
client/client/transport.py
client/common/__init__.py
client/common/decors.py
client/common/descriptors.py
client/common/errors.py
client/common/metaclass.py
client/common/utils.py
client/common/variables.py
client/log/__init__.py
client/log/config_client_log.py
client/log/config_server_log.py
client/unit_tests/__init__.py
client/unit_tests/test_client.py
client/unit_tests/test_server.py
client/unit_tests/test_utils.py
mess_test_client.egg-info/PKG-INFO
mess_test_client.egg-info/SOURCES.txt
mess_test_client.egg-info/dependency_links.txt
mess_test_client.egg-info/requires.txt
mess_test_client.egg-info/top_level.txt