Metadata-Version: 2.1
Name: mess-test-client
Version: 0.0.1
Summary: mess_test_client
Author: Aleksey Ovchinnikov
Author-email: denetor89@yandex.ru
License: UNKNOWN
Platform: UNKNOWN
